{
  "id": "566d6a63-2311-4db3-a4c8-9a2f592a7594",
  "prevId": "00000000-0000-0000-0000-000000000000",
  "version": "7",
  "dialect": "postgresql",
  "tables": {
    "public.admin": {
      "name": "admin",
      "schema": "",
      "columns": {
        "id": {
          "name": "id",
          "type": "uuid",
          "primaryKey": true,
          "notNull": true,
          "default": "gen_random_uuid()"
        },
        "name": {
          "name": "name",
          "type": "text",
          "primaryKey": false,
          "notNull": true
        },
        "google_id": {
          "name": "google_id",
          "type": "text",
          "primaryKey": false,
          "notNull": false
        },
        "github_id": {
          "name": "github_id",
          "type": "text",
          "primaryKey": false,
          "notNull": false
        }
      },
      "indexes": {},
      "foreignKeys": {},
      "compositePrimaryKeys": {},
      "uniqueConstraints": {}
    }
  },
  "enums": {},
  "schemas": {},
  "sequences": {},
  "_meta": {
    "columns": {},
    "schemas": {},
    "tables": {}
  }
}